openapi_client/__init__.py
openapi_client/api_client.py
openapi_client/configuration.py
openapi_client/exceptions.py
openapi_client/pydantic.py
openapi_client/rest.py
openapi_client/schemas.py
openapi_client/apis/__init__.py
openapi_client/apis/path_to_api.py
openapi_client/apis/tag_to_api.py
openapi_client/apis/paths/__init__.py
openapi_client/apis/paths/agents.py
openapi_client/apis/paths/agents_artifacts.py
openapi_client/apis/paths/agents_benchmarks.py
openapi_client/apis/paths/agents_bids.py
openapi_client/apis/paths/agents_tickets.py
openapi_client/apis/paths/repositories.py
openapi_client/apis/paths/users.py
openapi_client/apis/paths/users_artifacts.py
openapi_client/apis/paths/users_benchmarks.py
openapi_client/apis/paths/users_bids.py
openapi_client/apis/paths/users_tickets.py
openapi_client/apis/tags/__init__.py
openapi_client/apis/tags/default_api.py
openapi_client/model/__init__.py
openapi_client/model/agent.py
openapi_client/model/agents_response.py
openapi_client/model/artifact.py
openapi_client/model/artifacts_response.py
openapi_client/model/benchmark.py
openapi_client/model/benchmark_ticket.py
openapi_client/model/benchmarks_response.py
openapi_client/model/bid.py
openapi_client/model/bids_response.py
openapi_client/model/code.py
openapi_client/model/create_agent_request.py
openapi_client/model/create_artifact_request.py
openapi_client/model/create_benchmark_request.py
openapi_client/model/create_benchmark_ticket_request.py
openapi_client/model/create_bid_request.py
openapi_client/model/create_repository_request.py
openapi_client/model/create_ticket_request.py
openapi_client/model/create_user_request.py
openapi_client/model/error.py
openapi_client/model/errors_response.py
openapi_client/model/manage_user_artifact_request.py
openapi_client/model/manage_user_bid_request.py
openapi_client/model/repositories_response.py
openapi_client/model/repository.py
openapi_client/model/ticket.py
openapi_client/model/tickets_response.py
agent_marketplace_sdk-0.1.6.dist-info/METADATA
agent_marketplace_sdk-0.1.6.dist-info/WHEEL
agent_marketplace_sdk-0.1.6.dist-info/top_level.txt
agent_marketplace_sdk-0.1.6.dist-info/RECORD
